asgi_sage/__init__.py
asgi_sage/middleware.py
asgi_sage-0.1.2.dist-info/LICENSE
asgi_sage-0.1.2.dist-info/WHEEL
asgi_sage-0.1.2.dist-info/METADATA
asgi_sage-0.1.2.dist-info/RECORD
