Metadata-Version: 2.1
Name: asgi-sage
Version: 0.1.2
Summary: Security Headers for asgi apps
Home-page: https://github.com/jtmiclat/asgi-sage
License: MIT
Author: Jt Miclat
Author-email: jtmiclat@gmail.com
Requires-Python: >=3.6,<4.0
Classifier: License :: OSI Approved :: MIT License
Classifier: Programming Language :: Python :: 3
Classifier: Programming Language :: Python :: 3.6
Classifier: Programming Language :: Python :: 3.7
Classifier: Programming Language :: Python :: 3.8
Project-URL: Repository, https://github.com/jtmiclat/asgi-sage
